Metadata-Version: 2.4
Name: demo-greeter-mustafa
Version: 0.1.0
Summary: A minimal example package with a CLI 'greet'
Author-email: Your Name <you@example.com>
License: MIT License
Project-URL: Homepage, https://example.com/
Project-URL: Repository, https://github.com/yourname/demo-greeter-pkg
Classifier: Programming Language :: Python :: 3
Classifier: Programming Language :: Python :: 3 :: Only
Classifier: License :: OSI Approved :: MIT License
Classifier: Operating System :: OS Independent
Requires-Python: >=3.8
License-File: LICENSE
Dynamic: license-file
